{
  "project_info": {
    "project_number": "321254456613",
    "firebase_url": "https://crew-brew-44efc.firebaseio.com",
    "project_id": "crew-brew-44efc",
    "storage_bucket": "crew-brew-44efc.appspot.com"
  },
  "client": [
    {
      "client_info": {
        "mobilesdk_app_id": "1:321254456613:android:96173badf73478cb082ecc",
        "android_client_info": {
          "package_name": "tarek.dev.flutter.crewbrewapp"
        }
      },
      "oauth_client": [
        {
          "client_id": "321254456613-e3t4d5dmtjnieraeuhcrongaqc3jm6ip.apps.googleusercontent.com",
          "client_type": 3
        }
      ],
      "api_key": [
        {
          "current_key": "AIzaSyAkev0G2Ni5BK74wDVGA_GGAOGnPGjERSw"
        }
      ],
      "services": {
        "appinvite_service": {
          "other_platform_oauth_client": [
            {
              "client_id": "321254456613-e3t4d5dmtjnieraeuhcrongaqc3jm6ip.apps.googleusercontent.com",
              "client_type": 3
            }
          ]
        }
      }
    }
  ],
  "configuration_version": "1"
}